setup.py
jct/__init__.py
jct/jct.py
jct.egg-info/PKG-INFO
jct.egg-info/SOURCES.txt
jct.egg-info/dependency_links.txt
jct.egg-info/entry_points.txt
jct.egg-info/not-zip-safe
jct.egg-info/top_level.txt
test/test_jct.py